np_vmd/__init__.py
np_vmd/laplace_mdof.py
np_vmd/misc.py
np_vmd/sdof_funcs.py
np_vmd/tdof_MCK.py
np_vmd/tdof_odeint.py
np_vmd/tdof_response_inman.py
np_vmd/sho_class/SHO_sdof_class.py
np_vmd/sho_class/__init__.py
np_vmd/sho_class/example_sho.py
np_vmd/sho_class/sdof_sympy.py
np_vmd-0.1.1.dist-info/licenses/LICENSE
np_vmd-0.1.1.dist-info/METADATA
np_vmd-0.1.1.dist-info/WHEEL
np_vmd-0.1.1.dist-info/top_level.txt
np_vmd-0.1.1.dist-info/RECORD
