Metadata-Version: 2.4
Name: np-vmd
Version: 0.1.1
Summary: A package for Vibrations and Machine Dynamics
Author-email: "N. Papadakis" <npapnet@gmail.com>
Project-URL: Source, https://github.com/npapnet/np-vmd
Project-URL: Documentation, https://npapnet.github.io/np-vmd/
Classifier: Programming Language :: Python :: 3
Classifier: License :: OSI Approved :: MIT License
Classifier: Operating System :: OS Independent
Requires-Python: >=3.10
License-File: LICENSE
Requires-Dist: matplotlib
Requires-Dist: scipy
Requires-Dist: numpy
Requires-Dist: seaborn
Requires-Dist: pandas
Requires-Dist: openpyxl
Requires-Dist: ipykernel
Requires-Dist: jupyter
Provides-Extra: test
Requires-Dist: pytest; extra == "test"
Requires-Dist: pytest-cov; extra == "test"
Provides-Extra: dev
Requires-Dist: ruff; extra == "dev"
Requires-Dist: mypy; extra == "dev"
Provides-Extra: docs
Requires-Dist: sphinx; extra == "docs"
Requires-Dist: sphinx-rtd-theme; extra == "docs"
Requires-Dist: sphinxcontrib-mermaid; extra == "docs"
Dynamic: license-file
